stable_openai/__init__.py
stable_openai/backoff.py
stable_openai/key.py
stable_openai/rw_lock.py
stable_openai/tools.py
stable_openai-0.1.1.dist-info/LICENSE
stable_openai-0.1.1.dist-info/METADATA
stable_openai-0.1.1.dist-info/WHEEL
stable_openai-0.1.1.dist-info/top_level.txt
stable_openai-0.1.1.dist-info/RECORD
