Metadata-Version: 2.1
Name: stable-openai
Version: 0.1.1
Summary: StableOpenai is an enhanced framework for OpenAI, providing stable and efficient API request management. It allows the use of multiple API keys to increase request limits and ensures thread safety. The library features multi-key management, thread-safe operations for reliable requests in multi-threaded environments, and automatic fallback to alternate keys when API rate limits are reached. Ideal for developers looking to optimize interactions with OpenAI's services in robust, concurrent
Home-page: https://github.com/CZT0/StableOpenAI.git
Author: Jellow
Author-email: dvdx@foxmail.com
Requires-Python: >=3.7
License-File: LICENSE
Requires-Dist: openai
Requires-Dist: backoff
